tsconcat/__init__.py
tsconcat/b2t_columns.py
tsconcat/cli.py
tsconcat/concat.py
tsconcat/pretreeprint.py
tsconcat/utils.py
ba_tsconcat-0.1.4.dist-info/LICENSE
ba_tsconcat-0.1.4.dist-info/METADATA
ba_tsconcat-0.1.4.dist-info/WHEEL
ba_tsconcat-0.1.4.dist-info/entry_points.txt
ba_tsconcat-0.1.4.dist-info/RECORD
