Metadata-Version: 2.1
Name: ba-tsconcat
Version: 0.1.4
Summary: BIDS App and Python library for concatenating MRI time series.
License: LGPL-2.1
Author: CMI DAIR Center
Author-email: florian.rupprecht@childmind.org
Requires-Python: >=3.10,<4.0
Classifier: License :: OSI Approved
Classifier: Programming Language :: Python :: 3
Classifier: Programming Language :: Python :: 3.10
Classifier: Programming Language :: Python :: 3.11
Classifier: Programming Language :: Python :: 3.12
Requires-Dist: bids2table (>=0.1.0,<0.2.0)
Requires-Dist: nibabel (>=5.2.0,<6.0.0)
Requires-Dist: numpy (>=1.26.3,<2.0.0)
Requires-Dist: pandas (>=2.2.0,<3.0.0)
Requires-Dist: rich (>=13.4.2,<14.0.0)
